llamagym/__init__.py
llamagym/agent.py
llamagym-0.1.1.dist-info/LICENSE
llamagym-0.1.1.dist-info/METADATA
llamagym-0.1.1.dist-info/WHEEL
llamagym-0.1.1.dist-info/RECORD
