Metadata-Version: 2.1
Name: llamagym
Version: 0.1.1
Summary: Fine-tune LLM agents with online reinforcement learning
License: MIT
Author: Rohan Pandey
Requires-Python: >=3.9,<4.0
Classifier: License :: OSI Approved :: MIT License
Classifier: Programming Language :: Python :: 3
Classifier: Programming Language :: Python :: 3.9
Classifier: Programming Language :: Python :: 3.10
Classifier: Programming Language :: Python :: 3.11
Classifier: Programming Language :: Python :: 3.12
Requires-Dist: accelerate (>=0.21.0,<0.22.0)
Requires-Dist: bitsandbytes (>=0.40.0,<0.41.0)
Requires-Dist: gymnasium (>=0.29.1,<0.30.0)
Requires-Dist: peft (>=0.7.1,<0.8.0)
Requires-Dist: scipy (>=1.12.0,<2.0.0)
Requires-Dist: textworld (>=1.6.1,<2.0.0)
Requires-Dist: torch (>=2.1.2,<3.0.0)
Requires-Dist: transformers (>=4.36.2,<5.0.0)
Requires-Dist: trl (>=0.7.9,<0.8.0)
Requires-Dist: wandb (>=0.16.4,<0.17.0)
